drlgeb/__init__.py
drlgeb/example.py
drlgeb/ac/__init__.py
drlgeb/ac/a2c.py
drlgeb/ac/a3c.py
drlgeb/ac/batch_a3c.py
drlgeb/ac/model.py
drlgeb/common/__init__.py
drlgeb/common/agent.py
drlgeb/common/atari_wrappers.py
drlgeb/common/layers.py
drlgeb/common/logging_util.py
drlgeb/common/muultiprocess_env.py
drlgeb-0.0.1.dist-info/LICENSE
drlgeb-0.0.1.dist-info/METADATA
drlgeb-0.0.1.dist-info/WHEEL
drlgeb-0.0.1.dist-info/top_level.txt
drlgeb-0.0.1.dist-info/RECORD
