Metadata-Version: 2.1
Name: drlgeb
Version: 0.0.1
Summary: A sample but effective drl lib.
Home-page: https://github.com/mikuh/drlgeb
Author: geb
Author-email: 853934146@qq.com
License: UNKNOWN
Platform: UNKNOWN
Classifier: Programming Language :: Python :: 3
Classifier: License :: OSI Approved :: MIT License
Classifier: Operating System :: OS Independent
Requires-Python: >=3.7
Requires-Dist: numpy
Requires-Dist: tensorflow
Requires-Dist: gym
Requires-Dist: gym[atari]
